setup.cfg
setup.py
roamer/__init__.py
roamer/command.py
roamer/constant.py
roamer/database.py
roamer/directory.py
roamer/edit_directory.py
roamer/engine.py
roamer/entry.py
roamer/file_edit.py
roamer/main.py
roamer/record.py
roamer/session.py
roamer.egg-info/PKG-INFO
roamer.egg-info/SOURCES.txt
roamer.egg-info/dependency_links.txt
roamer.egg-info/entry_points.txt
roamer.egg-info/requires.txt
roamer.egg-info/top_level.txt