Metadata-Version: 1.1
Name: roamer
Version: 0.3.2
Summary: Plain Text File Explorer
Home-page: https://github.com/abaldwin88/roamer
Author: Alex Baldwin
Author-email: abaldwintech+hub@gmail.com
License: UNKNOWN
Download-URL: https://github.com/abaldwin88/roamer/archive/v0.3.2.zip
Keywords: explorer,plain text,directory
Platform: UNKNOWN
